personal_assistant/__init__.py
personal_assistant/commands.py
personal_assistant/main.py
personal_assistant/menus.py
personal_assistant/resources/preprocessing_params_v6.bin
personal_assistant/resources/tokenizer_v6.bin
personal_assistant/resources/intent_cat_v6/keras_metadata.pb
personal_assistant/resources/intent_cat_v6/saved_model.pb
personal_assistant/resources/intent_cat_v6/variables/variables.data-00000-of-00001
personal_assistant/resources/intent_cat_v6/variables/variables.index
personal_assistant/src/__init__.py
personal_assistant/src/messages.py
personal_assistant/src/personal_assistant.py
personal_assistant/src/utils.py
personal_assistant/src/contacts/__init__.py
personal_assistant/src/contacts/contacts.py
personal_assistant/src/contacts/fields.py
personal_assistant/src/contacts/record.py
personal_assistant/src/exceptions/__init__.py
personal_assistant/src/exceptions/exceptions.py
personal_assistant/src/intent_classifier/__init__.py
personal_assistant/src/intent_classifier/intent_classifier.py
personal_assistant/src/notes/__init__.py
personal_assistant/src/notes/note.py
personal_assistant/src/notes/notes.py
personal_assistant/utils/__init__.py
personal_assistant/utils/utils.py
py_brigade_personal_assistant-0.0.10.dist-info/LICENSE
py_brigade_personal_assistant-0.0.10.dist-info/METADATA
py_brigade_personal_assistant-0.0.10.dist-info/WHEEL
py_brigade_personal_assistant-0.0.10.dist-info/entry_points.txt
py_brigade_personal_assistant-0.0.10.dist-info/top_level.txt
py_brigade_personal_assistant-0.0.10.dist-info/RECORD
