Metadata-Version: 2.1
Name: py_brigade_personal_assistant
Version: 0.0.10
Summary: A personal assistant.
Home-page: https://github.com/nazarsmith/ppap7856-pythoneers-brigade-prjct
Author: Nazar Stakhovskyi
Author-email: nazarstahovsky@gmail.com
License: MIT
Classifier: Programming Language :: Python :: 3.8
Classifier: Programming Language :: Python :: 3.9
Classifier: Programming Language :: Python :: 3.10
Classifier: Programming Language :: Python :: 3.11
License-File: LICENSE
Requires-Dist: tensorflow ==2.12
Requires-Dist: numpy
Requires-Dist: prompt-toolkit
